{
  "meta": {
    "format": "vocabulary",
    "version": 1,
    "language": "",
    "source": "",
    "status": "pending",
    "tags": [
        "schaum17"
    ]
  },
  "data": [
    {
      "phrase": "小腹",
      "transcription": "xiǎofù",
      "grammar": "",
      "translation": "",
      "image": "",
      "audio": "",
      "video": "",
      "note": ""
    },
    {
      "phrase": "事故",
      "transcription": "shìgù",
      "grammar": "",
      "translation": "",
      "image": "",
      "audio": "",
      "video": "",
      "note": ""
    },
    {
      "phrase": "急性",
      "transcription": "jíxìng",
      "grammar": "",
      "translation": "",
      "image": "",
      "audio": "",
      "video": "",
      "note": ""
    },
    {
      "phrase": "创口贴",
      "transcription": "chuàngkǒu tiē",
      "grammar": "",
      "translation": "",
      "image": "",
      "audio": "",
      "video": "",
      "note": ""
    },
    {
      "phrase": "过敏",
      "transcription": "guòmǐn",
      "grammar": "",
      "translation": "",
      "image": "",
      "audio": "",
      "video": "",
      "note": ""
    },
    {
      "phrase": "过敏症",
      "transcription": "guòmǐnzhèng",
      "grammar": "",
      "translation": "",
      "image": "",
      "audio": "",
      "video": "",
      "note": ""
    },
    {
      "phrase": "救护车",
      "transcription": "jiùhù chē",
      "grammar": "",
      "translation": "",
      "image": "",
      "audio": "",
      "video": "",
      "note": ""
    },
    {
      "phrase": "麻药",
      "transcription": "máyào",
      "grammar": "",
      "translation": "",
      "image": "",
      "audio": "",
      "video": "",
      "note": ""
    },
    {
      "phrase": "麻醉师",
      "transcription": "mázuì shī",
      "grammar": "",
      "translation": "",
      "image": "",
      "audio": "",
      "video": "",
      "note": ""
    },
    {
      "phrase": "踝骨",
      "transcription": "huáigǔ",
      "grammar": "",
      "translation": "",
      "image": "",
      "audio": "",
      "video": "",
      "note": ""
    },
    {
      "phrase": "抗生素",
      "transcription": "kàngshēng sù",
      "grammar": "",
      "translation": "",
      "image": "",
      "audio": "",
      "video": "",
      "note": ""
    },
    {
      "phrase": "阑尾炎",
      "transcription": "lánwěi yán",
      "grammar": "",
      "translation": "",
      "image": "",
      "audio": "",
      "video": "",
      "note": ""
    },
    {
      "phrase": "盲肠炎",
      "transcription": "máng chángyán",
      "grammar": "",
      "translation": "",
      "image": "",
      "audio": "",
      "video": "",
      "note": ""
    },
    {
      "phrase": "阑尾",
      "transcription": "lánwěi",
      "grammar": "",
      "translation": "",
      "image": "",
      "audio": "",
      "video": "",
      "note": ""
    },
    {
      "phrase": "盲肠",
      "transcription": "mángcháng",
      "grammar": "",
      "translation": "",
      "image": "",
      "audio": "",
      "video": "",
      "note": ""
    },
    {
      "phrase": "胳膊",
      "transcription": "gēbo",
      "grammar": "",
      "translation": "",
      "image": "",
      "audio": "",
      "video": "",
      "note": ""
    },
    {
      "phrase": "手臂",
      "transcription": "shǒubì",
      "grammar": "",
      "translation": "",
      "image": "",
      "audio": "",
      "video": "",
      "note": ""
    },
    {
      "phrase": "关节炎",
      "transcription": "guānjié yán",
      "grammar": "",
      "translation": "",
      "image": "",
      "audio": "",
      "video": "",
      "note": ""
    },
    {
      "phrase": "背",
      "transcription": "bèi",
      "grammar": "",
      "translation": "",
      "image": "",
      "audio": "",
      "video": "",
      "note": ""
    },
    {
      "phrase": "绷带",
      "transcription": "bēngdài",
      "grammar": "",
      "translation": "",
      "image": "",
      "audio": "",
      "video": "",
      "note": ""
    },
    {
      "phrase": "包",
      "transcription": "bāo",
      "grammar": "",
      "translation": "",
      "image": "",
      "audio": "",
      "video": "",
      "note": ""
    },
    {
      "phrase": "血",
      "transcription": "xuè",
      "grammar": "",
      "translation": "",
      "image": "",
      "audio": "",
      "video": "",
      "note": ""
    },
    {
      "phrase": "血压",
      "transcription": "xuèyā",
      "grammar": "",
      "translation": "",
      "image": "",
      "audio": "",
      "video": "",
      "note": ""
    },
    {
      "phrase": "验血",
      "transcription": "yànxuè",
      "grammar": "",
      "translation": "",
      "image": "",
      "audio": "",
      "video": "",
      "note": ""
    },
    {
      "phrase": "血型",
      "transcription": "xuèxíng",
      "grammar": "",
      "translation": "",
      "image": "",
      "audio": "",
      "video": "",
      "note": ""
    },
    {
      "phrase": "骨折",
      "transcription": "gǔzhé",
      "grammar": "",
      "translation": "",
      "image": "",
      "audio": "",
      "video": "",
      "note": ""
    },
    {
      "phrase": "叫号",
      "transcription": "jiàohào",
      "grammar": "",
      "translation": "",
      "image": "",
      "audio": "",
      "video": "",
      "note": ""
    },
    {
      "phrase": "癌症",
      "transcription": "áizhèng",
      "grammar": "",
      "translation": "",
      "image": "",
      "audio": "",
      "video": "",
      "note": ""
    },
    {
      "phrase": "得",
      "transcription": "dé",
      "grammar": "",
      "translation": "",
      "image": "",
      "audio": "",
      "video": "",
      "note": ""
    },
    {
      "phrase": "测",
      "transcription": "cè",
      "grammar": "",
      "translation": "",
      "image": "",
      "audio": "",
      "video": "",
      "note": ""
    },
    {
      "phrase": "脸",
      "transcription": "liǎn",
      "grammar": "",
      "translation": "",
      "image": "",
      "audio": "",
      "video": "",
      "note": ""
    },
    {
      "phrase": "胸口",
      "transcription": "xiōngkǒu",
      "grammar": "",
      "translation": "",
      "image": "",
      "audio": "",
      "video": "",
      "note": ""
    },
    {
      "phrase": "水痘",
      "transcription": "shuǐdòu",
      "grammar": "",
      "translation": "",
      "image": "",
      "audio": "",
      "video": "",
      "note": ""
    },
    {
      "phrase": "发冷",
      "transcription": "fālěng",
      "grammar": "",
      "translation": "",
      "image": "",
      "audio": "",
      "video": "",
      "note": ""
    },
    {
      "phrase": "不通",
      "transcription": "bùtōng",
      "grammar": "",
      "translation": "",
      "image": "",
      "audio": "",
      "video": "",
      "note": ""
    },
    {
      "phrase": "咳嗽",
      "transcription": "késou",
      "grammar": "",
      "translation": "",
      "image": "",
      "audio": "",
      "video": "",
      "note": ""
    },
    {
      "phrase": "割破",
      "transcription": "gēpò",
      "grammar": "",
      "translation": "",
      "image": "",
      "audio": "",
      "video": "",
      "note": ""
    },
    {
      "phrase": "深",
      "transcription": "shēn",
      "grammar": "",
      "translation": "",
      "image": "",
      "audio": "",
      "video": "",
      "note": ""
    },
    {
      "phrase": "接生",
      "transcription": "jiēshēng",
      "grammar": "",
      "translation": "",
      "image": "",
      "audio": "",
      "video": "",
      "note": ""
    },
    {
      "phrase": "产房",
      "transcription": "chǎnfáng",
      "grammar": "",
      "translation": "",
      "image": "",
      "audio": "",
      "video": "",
      "note": ""
    },
    {
      "phrase": "拉肚子",
      "transcription": "lā dùzi",
      "grammar": "",
      "translation": "",
      "image": "",
      "audio": "",
      "video": "",
      "note": ""
    },
    {
      "phrase": "腹泻",
      "transcription": "fùxiè",
      "grammar": "",
      "translation": "",
      "image": "",
      "audio": "",
      "video": "",
      "note": ""
    },
    {
      "phrase": "头晕",
      "transcription": "tóuyūn",
      "grammar": "",
      "translation": "",
      "image": "",
      "audio": "",
      "video": "",
      "note": ""
    },
    {
      "phrase": "医生",
      "transcription": "yīshēng",
      "grammar": "",
      "translation": "",
      "image": "",
      "audio": "",
      "video": "",
      "note": ""
    },
    {
      "phrase": "值班医生",
      "transcription": "zhíbān yīshēng",
      "grammar": "",
      "translation": "",
      "image": "",
      "audio": "",
      "video": "",
      "note": ""
    },
    {
      "phrase": "抽",
      "transcription": "chōu",
      "grammar": "",
      "translation": "",
      "image": "",
      "audio": "",
      "video": "",
      "note": ""
    },
    {
      "phrase": "耳朵",
      "transcription": "ěrduo",
      "grammar": "",
      "translation": "",
      "image": "",
      "audio": "",
      "video": "",
      "note": ""
    },
    {
      "phrase": "胳膊肘",
      "transcription": "gēbó zhǒu",
      "grammar": "",
      "translation": "",
      "image": "",
      "audio": "",
      "video": "",
      "note": ""
    },
    {
      "phrase": "心电图",
      "transcription": "xīndiàntú",
      "grammar": "",
      "translation": "",
      "image": "",
      "audio": "",
      "video": "",
      "note": ""
    },
    {
      "phrase": "急诊室",
      "transcription": "jí zhěnshì",
      "grammar": "",
      "translation": "",
      "image": "",
      "audio": "",
      "video": "",
      "note": ""
    },
    {
      "phrase": "肠炎",
      "transcription": "chángyán",
      "grammar": "",
      "translation": "",
      "image": "",
      "audio": "",
      "video": "",
      "note": ""
    },
    {
      "phrase": "癫痫",
      "transcription": "diānxián",
      "grammar": "",
      "translation": "",
      "image": "",
      "audio": "",
      "video": "",
      "note": ""
    },
    {
      "phrase": "每隔四小时",
      "transcription": "měigé sì xiǎoshí",
      "grammar": "",
      "translation": "",
      "image": "",
      "audio": "",
      "video": "",
      "note": ""
    },
    {
      "phrase": "检查",
      "transcription": "jiǎnchá",
      "grammar": "",
      "translation": "",
      "image": "",
      "audio": "",
      "video": "",
      "note": ""
    },
    {
      "phrase": "大便",
      "transcription": "dàbiàn",
      "grammar": "",
      "translation": "",
      "image": "",
      "audio": "",
      "video": "",
      "note": ""
    },
    {
      "phrase": "发烧",
      "transcription": "fāshāo",
      "grammar": "",
      "translation": "",
      "image": "",
      "audio": "",
      "video": "",
      "note": ""
    },
    {
      "phrase": "填",
      "transcription": "tián",
      "grammar": "",
      "translation": "",
      "image": "",
      "audio": "",
      "video": "",
      "note": ""
    },
    {
      "phrase": "手指",
      "transcription": "shǒuzhǐ",
      "grammar": "",
      "translation": "",
      "image": "",
      "audio": "",
      "video": "",
      "note": ""
    },
    {
      "phrase": "流感",
      "transcription": "liúgǎn",
      "grammar": "",
      "translation": "",
      "image": "",
      "audio": "",
      "video": "",
      "note": ""
    },
    {
      "phrase": "脚",
      "transcription": "jiǎo",
      "grammar": "",
      "translation": "",
      "image": "",
      "audio": "",
      "video": "",
      "note": ""
    },
    {
      "phrase": "表",
      "transcription": "biǎo",
      "grammar": "",
      "translation": "",
      "image": "",
      "audio": "",
      "video": "",
      "note": ""
    },
    {
      "phrase": "打一针",
      "transcription": "dǎyīzhēn",
      "grammar": "",
      "translation": "",
      "image": "",
      "audio": "",
      "video": "",
      "note": ""
    },
    {
      "phrase": "生孩子",
      "transcription": "shēng háizi",
      "grammar": "",
      "translation": "",
      "image": "",
      "audio": "",
      "video": "",
      "note": ""
    },
    {
      "phrase": "淋巴",
      "transcription": "línbā",
      "grammar": "",
      "translation": "",
      "image": "",
      "audio": "",
      "video": "",
      "note": ""
    },
    {
      "phrase": "手",
      "transcription": "shǒu",
      "grammar": "",
      "translation": "",
      "image": "",
      "audio": "",
      "video": "",
      "note": ""
    },
    {
      "phrase": "感冒",
      "transcription": "gǎnmào",
      "grammar": "",
      "translation": "",
      "image": "",
      "audio": "",
      "video": "",
      "note": ""
    },
    {
      "phrase": "做手术",
      "transcription": "zuò shǒushù",
      "grammar": "",
      "translation": "",
      "image": "",
      "audio": "",
      "video": "",
      "note": ""
    },
    {
      "phrase": "头",
      "transcription": "tóu",
      "grammar": "",
      "translation": "",
      "image": "",
      "audio": "",
      "video": "",
      "note": ""
    },
    {
      "phrase": "心脏",
      "transcription": "xīnzàng",
      "grammar": "",
      "translation": "",
      "image": "",
      "audio": "",
      "video": "",
      "note": ""
    },
    {
      "phrase": "心脏病",
      "transcription": "xīnzàng bìng",
      "grammar": "",
      "translation": "",
      "image": "",
      "audio": "",
      "video": "",
      "note": ""
    },
    {
      "phrase": "胯骨",
      "transcription": "kuàgǔ",
      "grammar": "",
      "translation": "",
      "image": "",
      "audio": "",
      "video": "",
      "note": ""
    },
    {
      "phrase": "医院",
      "transcription": "yīyuàn",
      "grammar": "",
      "translation": "",
      "image": "",
      "audio": "",
      "video": "",
      "note": ""
    },
    {
      "phrase": "人体",
      "transcription": "réntǐ",
      "grammar": "",
      "translation": "",
      "image": "",
      "audio": "",
      "video": "",
      "note": ""
    },
    {
      "phrase": "疼",
      "transcription": "téng",
      "grammar": "",
      "translation": "",
      "image": "",
      "audio": "",
      "video": "",
      "note": ""
    },
    {
      "phrase": "分娩中",
      "transcription": "fènmiǎn zhōng",
      "grammar": "",
      "translation": "",
      "image": "",
      "audio": "",
      "video": "",
      "note": ""
    },
    {
      "phrase": "发炎",
      "transcription": "fāyán",
      "grammar": "",
      "translation": "",
      "image": "",
      "audio": "",
      "video": "",
      "note": ""
    },
    {
      "phrase": "注射",
      "transcription": "zhùshè",
      "grammar": "",
      "translation": "",
      "image": "",
      "audio": "",
      "video": "",
      "note": ""
    },
    {
      "phrase": "特护病房",
      "transcription": "tèhù bìng fáng",
      "grammar": "",
      "translation": "",
      "image": "",
      "audio": "",
      "video": "",
      "note": ""
    },
    {
      "phrase": "输液",
      "transcription": "shūyè",
      "grammar": "",
      "translation": "",
      "image": "",
      "audio": "",
      "video": "",
      "note": ""
    },
    {
      "phrase": "我这儿疼",
      "transcription": "wǒ zhèr téng",
      "grammar": "",
      "translation": "",
      "image": "",
      "audio": "",
      "video": "",
      "note": ""
    },
    {
      "phrase": "肾脏",
      "transcription": "shènzàng",
      "grammar": "",
      "translation": "",
      "image": "",
      "audio": "",
      "video": "",
      "note": ""
    },
    {
      "phrase": "膝盖",
      "transcription": "xīgài",
      "grammar": "",
      "translation": "",
      "image": "",
      "audio": "",
      "video": "",
      "note": ""
    },
    {
      "phrase": "阵痛",
      "transcription": "zhèntòng",
      "grammar": "",
      "translation": "",
      "image": "",
      "audio": "",
      "video": "",
      "note": ""
    },
    {
      "phrase": "化验",
      "transcription": "huàyàn",
      "grammar": "",
      "translation": "",
      "image": "",
      "audio": "",
      "video": "",
      "note": ""
    },
    {
      "phrase": "腿",
      "transcription": "tuǐ",
      "grammar": "",
      "translation": "",
      "image": "",
      "audio": "",
      "video": "",
      "note": ""
    },
    {
      "phrase": "肝脏",
      "transcription": "gānzàng",
      "grammar": "",
      "translation": "",
      "image": "",
      "audio": "",
      "video": "",
      "note": ""
    },
    {
      "phrase": "肺部",
      "transcription": "fèibù",
      "grammar": "",
      "translation": "",
      "image": "",
      "audio": "",
      "video": "",
      "note": ""
    },
    {
      "phrase": "麻疹",
      "transcription": "mázhěn",
      "grammar": "",
      "translation": "",
      "image": "",
      "audio": "",
      "video": "",
      "note": ""
    },
    {
      "phrase": "病史",
      "transcription": "bìngshǐ",
      "grammar": "",
      "translation": "",
      "image": "",
      "audio": "",
      "video": "",
      "note": ""
    },
    {
      "phrase": "医疗保险",
      "transcription": "yīliáo bǎoxiǎn",
      "grammar": "",
      "translation": "",
      "image": "",
      "audio": "",
      "video": "",
      "note": ""
    },
    {
      "phrase": "药",
      "transcription": "yào",
      "grammar": "",
      "translation": "",
      "image": "",
      "audio": "",
      "video": "",
      "note": ""
    },
    {
      "phrase": "月经",
      "transcription": "yuèjīng",
      "grammar": "",
      "translation": "",
      "image": "",
      "audio": "",
      "video": "",
      "note": ""
    },
    {
      "phrase": "精神病",
      "transcription": "jīngshén bìng",
      "grammar": "",
      "translation": "",
      "image": "",
      "audio": "",
      "video": "",
      "note": ""
    },
    {
      "phrase": "嘴",
      "transcription": "zuǐ",
      "grammar": "",
      "translation": "",
      "image": "",
      "audio": "",
      "video": "",
      "note": ""
    },
    {
      "phrase": "流行性",
      "transcription": "liúxíngxìng",
      "grammar": "",
      "translation": "",
      "image": "",
      "audio": "",
      "video": "",
      "note": ""
    },
    {
      "phrase": "腮腺炎",
      "transcription": "sāi xiànyán",
      "grammar": "",
      "translation": "",
      "image": "",
      "audio": "",
      "video": "",
      "note": ""
    },
    {
      "phrase": "恶心",
      "transcription": "ěxīn",
      "grammar": "",
      "translation": "",
      "image": "",
      "audio": "",
      "video": "",
      "note": ""
    },
    {
      "phrase": "鼻子",
      "transcription": "bízi",
      "grammar": "",
      "translation": "",
      "image": "",
      "audio": "",
      "video": "",
      "note": ""
    },
    {
      "phrase": "护士",
      "transcription": "hùshi",
      "grammar": "",
      "translation": "",
      "image": "",
      "audio": "",
      "video": "",
      "note": ""
    },
    {
      "phrase": "观察",
      "transcription": "guānchá",
      "grammar": "",
      "translation": "",
      "image": "",
      "audio": "",
      "video": "",
      "note": ""
    },
    {
      "phrase": "产科医生",
      "transcription": "chǎnkē yīshēng",
      "grammar": "",
      "translation": "",
      "image": "",
      "audio": "",
      "video": "",
      "note": ""
    },
    {
      "phrase": "拄拐杖",
      "transcription": "zhǔ guǎizhàng",
      "grammar": "",
      "translation": "",
      "image": "",
      "audio": "",
      "video": "",
      "note": ""
    },
    {
      "phrase": "实习医生",
      "transcription": "shíxí yīshēng",
      "grammar": "",
      "translation": "",
      "image": "",
      "audio": "",
      "video": "",
      "note": ""
    },
    {
      "phrase": "张开",
      "transcription": "zhāngkāi",
      "grammar": "",
      "translation": "",
      "image": "",
      "audio": "",
      "video": "",
      "note": ""
    },
    {
      "phrase": "动手术",
      "transcription": "dòng shǒushù",
      "grammar": "",
      "translation": "",
      "image": "",
      "audio": "",
      "video": "",
      "note": ""
    },
    {
      "phrase": "手术室",
      "transcription": "shǒushù shì",
      "grammar": "",
      "translation": "",
      "image": "",
      "audio": "",
      "video": "",
      "note": ""
    },
    {
      "phrase": "手术台",
      "transcription": "shǒushù tái",
      "grammar": "",
      "translation": "",
      "image": "",
      "audio": "",
      "video": "",
      "note": ""
    },
    {
      "phrase": "手术",
      "transcription": "shǒushù",
      "grammar": "",
      "translation": "",
      "image": "",
      "audio": "",
      "video": "",
      "note": ""
    },
    {
      "phrase": "脏器",
      "transcription": "zàngqì",
      "grammar": "",
      "translation": "",
      "image": "",
      "audio": "",
      "video": "",
      "note": ""
    },
    {
      "phrase": "输氧",
      "transcription": "shūyǎng",
      "grammar": "",
      "translation": "",
      "image": "",
      "audio": "",
      "video": "",
      "note": ""
    },
    {
      "phrase": "病人",
      "transcription": "bìngrén",
      "grammar": "",
      "translation": "",
      "image": "",
      "audio": "",
      "video": "",
      "note": ""
    },
    {
      "phrase": "青霉素",
      "transcription": "qīngméisù",
      "grammar": "",
      "translation": "",
      "image": "",
      "audio": "",
      "video": "",
      "note": ""
    },
    {
      "phrase": "安置",
      "transcription": "ānzhì",
      "grammar": "",
      "translation": "",
      "image": "",
      "audio": "",
      "video": "",
      "note": ""
    },
    {
      "phrase": "小儿麻痹症",
      "transcription": "xiǎo'ér mábì zhèng",
      "grammar": "",
      "translation": "",
      "image": "",
      "audio": "",
      "video": "",
      "note": ""
    },
    {
      "phrase": "怀孕",
      "transcription": "huáiyùn",
      "grammar": "",
      "translation": "",
      "image": "",
      "audio": "",
      "video": "",
      "note": ""
    },
    {
      "phrase": "做准备",
      "transcription": "zuò zhǔnbèi",
      "grammar": "",
      "translation": "",
      "image": "",
      "audio": "",
      "video": "",
      "note": ""
    },
    {
      "phrase": "开",
      "transcription": "kāi",
      "grammar": "",
      "translation": "",
      "image": "",
      "audio": "",
      "video": "",
      "note": ""
    },
    {
      "phrase": "手术后情况",
      "transcription": "shǒushù hòu qíngkuàng",
      "grammar": "",
      "translation": "",
      "image": "",
      "audio": "",
      "video": "",
      "note": ""
    },
    {
      "phrase": "脉搏",
      "transcription": "màibó",
      "grammar": "",
      "translation": "",
      "image": "",
      "audio": "",
      "video": "",
      "note": ""
    },
    {
      "phrase": "推",
      "transcription": "tuī",
      "grammar": "",
      "translation": "",
      "image": "",
      "audio": "",
      "video": "",
      "note": ""
    },
    {
      "phrase": "上石膏",
      "transcription": "shàng shígāo",
      "grammar": "",
      "translation": "",
      "image": "",
      "audio": "",
      "video": "",
      "note": ""
    },
    {
      "phrase": "观察室",
      "transcription": "guānchá shì",
      "grammar": "",
      "translation": "",
      "image": "",
      "audio": "",
      "video": "",
      "note": ""
    },
    {
      "phrase": "挂号",
      "transcription": "guàhào",
      "grammar": "",
      "translation": "",
      "image": "",
      "audio": "",
      "video": "",
      "note": ""
    },
    {
      "phrase": "挂号处",
      "transcription": "guàhào chù",
      "grammar": "",
      "translation": "",
      "image": "",
      "audio": "",
      "video": "",
      "note": ""
    },
    {
      "phrase": "正常",
      "transcription": "zhèngcháng",
      "grammar": "",
      "translation": "",
      "image": "",
      "audio": "",
      "video": "",
      "note": ""
    },
    {
      "phrase": "切除",
      "transcription": "qiēchú",
      "grammar": "",
      "translation": "",
      "image": "",
      "audio": "",
      "video": "",
      "note": ""
    },
    {
      "phrase": "卷起",
      "transcription": "juǎnqǐ",
      "grammar": "",
      "translation": "",
      "image": "",
      "audio": "",
      "video": "",
      "note": ""
    },
    {
      "phrase": "流鼻涕",
      "transcription": "liú bítì",
      "grammar": "",
      "translation": "",
      "image": "",
      "audio": "",
      "video": "",
      "note": ""
    },
    {
      "phrase": "看病",
      "transcription": "kànbìng",
      "grammar": "",
      "translation": "",
      "image": "",
      "audio": "",
      "video": "",
      "note": ""
    },
    {
      "phrase": "固定骨头",
      "transcription": "gùdìng gǔtóu",
      "grammar": "",
      "translation": "",
      "image": "",
      "audio": "",
      "video": "",
      "note": ""
    },
    {
      "phrase": "肩膀",
      "transcription": "jiānbǎng",
      "grammar": "",
      "translation": "",
      "image": "",
      "audio": "",
      "video": "",
      "note": ""
    },
    {
      "phrase": "难受",
      "transcription": "nánshòu",
      "grammar": "",
      "translation": "",
      "image": "",
      "audio": "",
      "video": "",
      "note": ""
    },
    {
      "phrase": "袖子",
      "transcription": "xiùzi",
      "grammar": "",
      "translation": "",
      "image": "",
      "audio": "",
      "video": "",
      "note": ""
    },
    {
      "phrase": "扭伤",
      "transcription": "niǔshāng",
      "grammar": "",
      "translation": "",
      "image": "",
      "audio": "",
      "video": "",
      "note": ""
    },
    {
      "phrase": "听诊器",
      "transcription": "tīngzhěn qì",
      "grammar": "",
      "translation": "",
      "image": "",
      "audio": "",
      "video": "",
      "note": ""
    },
    {
      "phrase": "缝合",
      "transcription": "fénghé",
      "grammar": "",
      "translation": "",
      "image": "",
      "audio": "",
      "video": "",
      "note": ""
    },
    {
      "phrase": "胃疼",
      "transcription": "wèiténg",
      "grammar": "",
      "translation": "",
      "image": "",
      "audio": "",
      "video": "",
      "note": ""
    },
    {
      "phrase": "肚子疼",
      "transcription": "dùzi téng",
      "grammar": "",
      "translation": "",
      "image": "",
      "audio": "",
      "video": "",
      "note": ""
    },
    {
      "phrase": "担架",
      "transcription": "dānjià",
      "grammar": "",
      "translation": "",
      "image": "",
      "audio": "",
      "video": "",
      "note": ""
    },
    {
      "phrase": "外科医生",
      "transcription": "wàikē yīshēng",
      "grammar": "",
      "translation": "",
      "image": "",
      "audio": "",
      "video": "",
      "note": ""
    },
    {
      "phrase": "肿",
      "transcription": "zhǒng",
      "grammar": "",
      "translation": "",
      "image": "",
      "audio": "",
      "video": "",
      "note": ""
    },
    {
      "phrase": "症状",
      "transcription": "zhèngzhuàng",
      "grammar": "",
      "translation": "",
      "image": "",
      "audio": "",
      "video": "",
      "note": ""
    },
    {
      "phrase": "片",
      "transcription": "piān",
      "grammar": "",
      "translation": "",
      "image": "",
      "audio": "",
      "video": "",
      "note": ""
    },
    {
      "phrase": "量体温",
      "transcription": "liáng tǐwēn",
      "grammar": "",
      "translation": "",
      "image": "",
      "audio": "",
      "video": "",
      "note": ""
    },
    {
      "phrase": "嗓子",
      "transcription": "sǎngzi",
      "grammar": "",
      "translation": "",
      "image": "",
      "audio": "",
      "video": "",
      "note": ""
    },
    {
      "phrase": "喉咙",
      "transcription": "hóulóng",
      "grammar": "",
      "translation": "",
      "image": "",
      "audio": "",
      "video": "",
      "note": ""
    },
    {
      "phrase": "扁桃腺",
      "transcription": "biǎntáo xiàn",
      "grammar": "",
      "translation": "",
      "image": "",
      "audio": "",
      "video": "",
      "note": ""
    },
    {
      "phrase": "镇静剂",
      "transcription": "zhènjìng jì",
      "grammar": "",
      "translation": "",
      "image": "",
      "audio": "",
      "video": "",
      "note": ""
    },
    {
      "phrase": "肺结核",
      "transcription": "fèijiéhé",
      "grammar": "",
      "translation": "",
      "image": "",
      "audio": "",
      "video": "",
      "note": ""
    },
    {
      "phrase": "不舒服",
      "transcription": "bù shūfu",
      "grammar": "",
      "translation": "",
      "image": "",
      "audio": "",
      "video": "",
      "note": ""
    },
    {
      "phrase": "意外",
      "transcription": "yìwài",
      "grammar": "",
      "translation": "",
      "image": "",
      "audio": "",
      "video": "",
      "note": ""
    },
    {
      "phrase": "小便",
      "transcription": "xiǎobiàn",
      "grammar": "",
      "translation": "",
      "image": "",
      "audio": "",
      "video": "",
      "note": ""
    },
    {
      "phrase": "性病",
      "transcription": "xìngbìng",
      "grammar": "",
      "translation": "",
      "image": "",
      "audio": "",
      "video": "",
      "note": ""
    },
    {
      "phrase": "主要",
      "transcription": "zhǔyào",
      "grammar": "",
      "translation": "",
      "image": "",
      "audio": "",
      "video": "",
      "note": ""
    },
    {
      "phrase": "吐",
      "transcription": "tù",
      "grammar": "",
      "translation": "",
      "image": "",
      "audio": "",
      "video": "",
      "note": ""
    },
    {
      "phrase": "腰",
      "transcription": "yāo",
      "grammar": "",
      "translation": "",
      "image": "",
      "audio": "",
      "video": "",
      "note": ""
    },
    {
      "phrase": "候诊室",
      "transcription": "hòuzhěn shì",
      "grammar": "",
      "translation": "",
      "image": "",
      "audio": "",
      "video": "",
      "note": ""
    },
    {
      "phrase": "轮椅",
      "transcription": "lúnyǐ",
      "grammar": "",
      "translation": "",
      "image": "",
      "audio": "",
      "video": "",
      "note": ""
    },
    {
      "phrase": "伤口",
      "transcription": "shāngkǒu",
      "grammar": "",
      "translation": "",
      "image": "",
      "audio": "",
      "video": "",
      "note": ""
    },
    {
      "phrase": "手腕",
      "transcription": "shǒuwàn",
      "grammar": "",
      "translation": "",
      "image": "",
      "audio": "",
      "video": "",
      "note": ""
    }
  ]
}